odoo/addons/auth_oauth_multi_token/README.rst
odoo/addons/auth_oauth_multi_token/__init__.py
odoo/addons/auth_oauth_multi_token/__manifest__.py
odoo/addons/auth_oauth_multi_token/models/__init__.py
odoo/addons/auth_oauth_multi_token/models/auth_oauth_multi_token.py
odoo/addons/auth_oauth_multi_token/models/res_users.py
odoo/addons/auth_oauth_multi_token/security/ir.model.access.csv
odoo/addons/auth_oauth_multi_token/tests/__init__.py
odoo/addons/auth_oauth_multi_token/tests/test_multi_token.py
odoo/addons/auth_oauth_multi_token/views/res_users.xml
odoo11_addon_auth_oauth_multi_token-11.0.1.0.0.dist-info/DESCRIPTION.rst
odoo11_addon_auth_oauth_multi_token-11.0.1.0.0.dist-info/METADATA
odoo11_addon_auth_oauth_multi_token-11.0.1.0.0.dist-info/RECORD
odoo11_addon_auth_oauth_multi_token-11.0.1.0.0.dist-info/WHEEL
odoo11_addon_auth_oauth_multi_token-11.0.1.0.0.dist-info/metadata.json
odoo11_addon_auth_oauth_multi_token-11.0.1.0.0.dist-info/top_level.txt
